.appveyor.yml
.bumpversion.cfg
.cookiecutterrc
.coveragerc
.dockerignore
.editorconfig
.pre-commit-config.yaml
.travis.yml
AUTHORS.rst
CHANGELOG.rst
CONTRIBUTING.rst
Dockerfile
LICENSE
MANIFEST.in
README.rst
requirements-dev.txt
setup.cfg
setup.py
tox.ini
ci/appveyor-with-compiler.cmd
ci/bootstrap.py
ci/requirements.txt
ci/templates/.appveyor.yml
ci/templates/.travis.yml
docs/authors.rst
docs/changelog.rst
docs/conf.py
docs/contributing.rst
docs/index.rst
docs/installation.rst
docs/readme.rst
docs/requirements.txt
docs/spelling_wordlist.txt
docs/usage.rst
docs/reference/index.rst
docs/reference/oasapi.rst
docs/samples/swagger_petstore.json
docs/samples/swagger_petstore.yaml
docs/samples/swagger_petstore_unused_elements.json
docs/samples/swagger_petstore_with_errors.json
src/oasapi/__init__.py
src/oasapi/__main__.py
src/oasapi/common.py
src/oasapi/events.py
src/oasapi/filter.py
src/oasapi/jspaths.py
src/oasapi/prune.py
src/oasapi/timer.py
src/oasapi/validation.py
src/oasapi.egg-info/PKG-INFO
src/oasapi.egg-info/SOURCES.txt
src/oasapi.egg-info/dependency_links.txt
src/oasapi.egg-info/entry_points.txt
src/oasapi.egg-info/not-zip-safe
src/oasapi.egg-info/requires.txt
src/oasapi.egg-info/top_level.txt
src/oasapi/cli/__init__.py
src/oasapi/cli/cli.py
src/oasapi/cli/common.py
src/oasapi/schemas/schema_swagger.json
tests/test_cli.py
tests/test_common.py
tests/test_filter.py
tests/test_prune.py
tests/test_validation.py