Metadata-Version: 1.2
Name: oasapi
Version: 0.1.17
Summary: Python library for Web APIs leveraging OpenAPI/Swagger specification
Home-page: https://github.com/sdementen/oasapi
Author: Sebastien de Menten
Author-email: sdementen@gmail.com
License: BSD-3-Clause
Project-URL: Documentation, https://oasapi.readthedocs.io/
Project-URL: Changelog, https://oasapi.readthedocs.io/en/latest/changelog.html
Project-URL: Issue Tracker, https://github.com/sdementen/oasapi/issues
Platform: UNKNOWN
Classifier: Development Status :: 5 - Production/Stable
Classifier: Intended Audience :: Developers
Classifier: License :: OSI Approved :: BSD License
Classifier: Operating System :: Unix
Classifier: Operating System :: POSIX
Classifier: Operating System :: Microsoft :: Windows
Classifier: Programming Language :: Python
Classifier: Programming Language :: Python :: 3
Classifier: Programming Language :: Python :: 3.6
Classifier: Programming Language :: Python :: 3.7
Classifier: Programming Language :: Python :: 3.8
Classifier: Programming Language :: Python :: Implementation :: CPython
Classifier: Programming Language :: Python :: Implementation :: PyPy
Classifier: Topic :: Utilities
Requires-Python: >=3.6.*
